pachong/__init__.py
pachong/face_compare.py
pachong/setting_basic.py
pachong/setting_db.py
pachong/setting_logger.py
pachong/common/__init__.py
pachong/common/timeout.py
pachong/crawler/__init__.py
pachong/crawler/pachong.py
pachong/crawler/pachong_kai.py
pachong/crawler/common/__init__.py
pachong/crawler/common/base62.py
pachong/crawler/common/exceptions.py
pachong/crawler/common/utils.py
pachong/crawler/taobao/__init__.py
pachong/crawler/taobao/parsers.py
pachong/crawler/taobao/taobao.py
pachong/crawler/weibo/__init__.py
pachong/crawler/weibo/login.py
pachong/crawler/weibo/parsers.py
pachong/crawler/weibo/weibo.py
pachong/crawler/yizhibo/__init__.py
pachong/crawler/yizhibo/parsers.py
pachong/crawler/yizhibo/yizhibo.py
pachong/database/__init__.py
pachong/database/base.py
pachong/database/mongodb.py
pachong/fetcher/__init__.py
pachong/fetcher/base.py
pachong/fetcher/selenium_.py
pachong/fetcher/test.py
pachong/fetcher/bs4/__init__.py
pachong/fetcher/requests/__init__.py
pachong/fetcher/requests/requests.py
pachong/fetcher/selenium/__init__.py
pachong/fetcher/selenium/selenium.py
pachong/fetcher/selenium/webdrivers.py
pachong/notifier/__init__.py
pachong/notifier/pushbullet.py
pachong/proxy/__init__.py
pachong/proxy/valid.py
pachong-0.0.80.dist-info/DESCRIPTION.rst
pachong-0.0.80.dist-info/METADATA
pachong-0.0.80.dist-info/RECORD
pachong-0.0.80.dist-info/WHEEL
pachong-0.0.80.dist-info/metadata.json
pachong-0.0.80.dist-info/top_level.txt
pachong-0.0.80.dist-info/zip-safe
pachong1/Soyoung.py
pachong1/__init__.py
pachong1/base62.py
pachong1/example_weibotimeline.py
pachong1/instagram.py
pachong1/pachong.py
pachong1/parsers_utils.py
pachong1/taobao.py
pachong1/taobao_parsers.py
pachong1/weibo.py
pachong1/weibo_login.py
pachong1/weibo_parsers.py
pachong1/yizhibo.py
pachong1/yizhibo_parsers.py
