Metadata-Version: 2.0
Name: pachong
Version: 0.0.80
Summary: python webscraping framework
Home-page: https://github.com/PhantomKidding/
Author: cchen
Author-email: phantomkidding@gmail.com
License: MIT License
Keywords: requests,retries,web-scraping,auto-sleeping
Platform: any
Requires-Dist: requests
Requires-Dist: bs4
Requires-Dist: selenium
Requires-Dist: pushbullet.py
Requires-Dist: tqdm
Requires-Dist: future
Requires-Dist: six
Requires-Dist: pytz
Requires-Dist: lxml
Requires-Dist: browsermob-proxy
Requires-Dist: pymongo
Requires-Dist: rsa
